buaa_open_source_22371550_test_package2/__init__.py
buaa_open_source_22371550_test_package2/parser.py
buaa_open_source_22371550_test_package2-0.2.dist-info/METADATA
buaa_open_source_22371550_test_package2-0.2.dist-info/WHEEL
buaa_open_source_22371550_test_package2-0.2.dist-info/top_level.txt
buaa_open_source_22371550_test_package2-0.2.dist-info/RECORD
